main.py
Pythondeveloper_task_5-1.0.0.dist-info/METADATA
Pythondeveloper_task_5-1.0.0.dist-info/WHEEL
Pythondeveloper_task_5-1.0.0.dist-info/top_level.txt
Pythondeveloper_task_5-1.0.0.dist-info/RECORD
